{
  "bc": {
    "top_terms": [
      {
        "term": "columbia",
        "score": 0.4953
      },
      {
        "term": "appropriation",
        "score": 0.4658
      },
      {
        "term": "voted",
        "score": 0.451
      },
      {
        "term": "cts",
        "score": 0.4489
      },
      {
        "term": "kamloops",
        "score": 0.4131
      },
      {
        "term": "headman",
        "score": 0.4068
      },
      {
        "term": "thence",
        "score": 0.3225
      },
      {
        "term": "cowichan",
        "score": 0.3077
      },
      {
        "term": "begg",
        "score": 0.3056
      },
      {
        "term": "inlet",
        "score": 0.2972
      },
      {
        "term": "personal",
        "score": 0.2887
      },
      {
        "term": "touchwood",
        "score": 0.2656
      },
      {
        "term": "canneries",
        "score": 0.2613
      },
      {
        "term": "lev",
        "score": 0.2613
      },
      {
        "term": "commissioner",
        "score": 0.2592
      },
      {
        "term": "okanagan",
        "score": 0.2529
      },
      {
        "term": "natives",
        "score": 0.2445
      },
      {
        "term": "receipts",
        "score": 0.236
      },
      {
        "term": "boarding",
        "score": 0.2255
      },
      {
        "term": "irrigation",
        "score": 0.2213
      }
    ],
    "n_sections": 228,
    "n_agents": 43,
    "n_tokens": 192387
  },
  "prairies": {
    "top_terms": [
      {
        "term": "mos",
        "score": 0.4287
      },
      {
        "term": "battleford",
        "score": 0.3356
      },
      {
        "term": "page",
        "score": 0.3035
      },
      {
        "term": "boarding",
        "score": 0.3004
      },
      {
        "term": "corral",
        "score": 0.2858
      },
      {
        "term": "blackfoot",
        "score": 0.2787
      },
      {
        "term": "audited",
        "score": 0.2662
      },
      {
        "term": "commissioner",
        "score": 0.258
      },
      {
        "term": "warehouse",
        "score": 0.2564
      },
      {
        "term": "cts",
        "score": 0.2477
      },
      {
        "term": "pas",
        "score": 0.244
      },
      {
        "term": "duck",
        "score": 0.2285
      },
      {
        "term": "saskatchewan",
        "score": 0.2187
      },
      {
        "term": "yds",
        "score": 0.2073
      },
      {
        "term": "stack",
        "score": 0.1989
      },
      {
        "term": "cree",
        "score": 0.1939
      },
      {
        "term": "touchwood",
        "score": 0.1923
      },
      {
        "term": "assiniboine",
        "score": 0.1867
      },
      {
        "term": "offal",
        "score": 0.1863
      },
      {
        "term": "cumberland",
        "score": 0.1722
      }
    ],
    "n_sections": 596,
    "n_agents": 247,
    "n_tokens": 784208
  },
  "quebec": {
    "top_terms": [
      {
        "term": "notre",
        "score": 0.3585
      },
      {
        "term": "dame",
        "score": 0.3585
      },
      {
        "term": "delormier",
        "score": 0.3346
      },
      {
        "term": "walbank",
        "score": 0.3107
      },
      {
        "term": "snow-shoes",
        "score": 0.3107
      },
      {
        "term": "bethsiamits",
        "score": 0.2868
      },
      {
        "term": "jocks",
        "score": 0.2629
      },
      {
        "term": "grande",
        "score": 0.239
      },
      {
        "term": "moisie",
        "score": 0.2382
      },
      {
        "term": "lacrosses",
        "score": 0.2151
      },
      {
        "term": "mistress",
        "score": 0.1912
      },
      {
        "term": "montour",
        "score": 0.1912
      },
      {
        "term": "natashquan",
        "score": 0.1764
      },
      {
        "term": "mclea",
        "score": 0.1673
      },
      {
        "term": "arnaud",
        "score": 0.1673
      },
      {
        "term": "masknaro",
        "score": 0.1673
      },
      {
        "term": "bitobee",
        "score": 0.1434
      },
      {
        "term": "otis",
        "score": 0.1411
      },
      {
        "term": "lebel",
        "score": 0.1323
      },
      {
        "term": "shantying",
        "score": 0.1195
      }
    ],
    "n_sections": 175,
    "n_agents": 39,
    "n_tokens": 45968
  },
  "method": {
    "total_sections_considered": 2123,
    "dropped_no_grounded_agents": 434,
    "dropped_outside_three_regions": 651,
    "dropped_no_majority_region": 28,
    "min_term_frequency": 5,
    "note": "TF-IDF computed across three region-level \"documents\". Each section was assigned to a region by majority vote of its grounded LINCS Indian Affairs Agents, never by string matching on the section text."
  }
}